Workbook

Sheet README
A1: Customer Segmentation & Retention Analytics – analytical workings
A2: SYNTHETIC DATA · fictional customers · values in USD · author: Ahsan Anas (built with AI assistance)
A4: Sheet | B4: Contents
A5: Assumptions | B5: Every model input in one place (blue = editable). Change a value and Scoring + Segment_Summary recalculate.
A6: Data_Clean | B6: 4,000 cleaned synthetic customers – the inputs to the scorecard (blank = not available, never imputed).
A7: Scoring | B7: Live formulas: 8 revenue components → est. annual revenue; 5 engagement components → REI; value band × engagement band → segment.
A8: Segment_Summary | B8: Live COUNTIFS / SUMIFS / AVERAGEIFS profile of each segment.
A9: Scenarios | B9: Hypothetical interventions with formula-driven sizing (assumptions in blue). Illustrative only.
A10: Pilot | B10: Holdout pilot sizing with a live minimum-detectable-effect formula (indicative).
A11: Sensitivity | B11: Alternative weights and cut-offs (computed in Python): share of customers keeping the same segment.
A12: Signals_Model | B12: Warning-signal lift table, attrition-model deciles and coefficients (Python, synthetic outcome).
A13: DQ_Log | B13: Every cleaning rule: rows affected, action, rationale.
A14: Data_Dictionary | B14: Field definitions.
A16: Labels | B16: Synthetic observation = what the fictional data shows · Model assumption = a modelling choice · Hypothetical = an intervention scenario, not a result.
A17: Reconciliation | B17: src/validate.py confirms Scoring formulas reproduce the Python revenue, REI and segment for every customer.

Sheet Assumptions
A1: Model assumptions (blue = editable inputs)
A2: All values are illustrative assumptions for a synthetic portfolio
A4: Revenue proxy (annual) | D4: Sum of weights (must be 100)
A5: current account margin | B5: 0.025 | D5: =SUM(Assumptions!$B$15,Assumptions!$B$16,Assumptions!$B$17,Assumptions!$B$18,Assumptions!$B$19) -> 100
A6: savings margin | B6: 0.012
A7: term deposit margin | B7: 0.008
A8: investment fee | B8: 0.0075
A9: mortgage margin | B9: 0.011
A10: personal loan margin | B10: 0.045
A11: card revolve margin | B11: 0.12
A12: card interchange | B12: 0.012
A13: card revolving share | B13: 0.5
A14: Engagement index weights
A15: weight: recency | B15: 30
A16: weight: frequency | B16: 20
A17: weight: digital | B17: 15
A18: weight: adoption | B18: 20
A19: weight: loyalty | B19: 15
A20: recency half-life (days) | B20: 30
A21: frequency cap (90-day txns) | B21: 120
A22: login cap (30-day logins) | B22: 20
A23: adoption cap (products beyond current account) | B23: 4
A24: tenure cap (years) | B24: 10
A25: Segment bands
A26: value band High ≥ (USD) | B26: 1500
A27: value band Mid ≥ (USD) | B27: 400
A28: engagement band High ≥ (REI) | B28: 70
A29: engagement band Mid ≥ (REI) | B29: 50
A31: Segment rule table
A32: Key (value|engagement) | B32: Segment
A33: High|High | B33: Premier Advocates
A34: High|Mid | B34: Established Core
A35: Mid|Mid | B35: Established Core
A36: High|Low | B36: Affluent Drifters
A37: Mid|High | B37: Engaged Builders
A38: Low|High | B38: Engaged Builders
A39: Mid|Low | B39: Light Touch
A40: Low|Mid | B40: Light Touch
A41: Low|Low | B41: Dormant & Low Value

Sheet Data_Clean
A1: Cleaned synthetic customers (4,000)
A2: Blank = not available in the source; nothing imputed
A4: customer_id | B4: region | C4: age | D4: main_bank_flag | E4: tenure_months | F4: num_products | G4: current_account_avg_bal_3m | H4: savings_balance | I4: term_deposit_balance | J4: investment_balance | K4: mortgage_balance | L4: personal_loan_balance | M4: credit_card_limit | N4: card_utilisation_pct | O4: card_spend_90d | P4: days_since_txn | Q4: txn_count_90d | R4: app_logins_30d | S4: digital_txn_share | T4: complaints_12m | U4: attrited_next_6m | V4: attrition_risk_model | W4: dq_flags
A5: CX100001 | B5: Metro | C5: 39 | D5: N | E5: 43 | F5: 3 | G5: 4133.29 | H5: 0 | I5: 0 | J5: 39544.71 | K5: 0 | L5: 0 | M5: 19400 | N5: 33.7 | O5: 234.31 | P5: 0 | Q5: 26 | R5: 11 | S5: 0.723 | T5: 0 | U5: 0 | V5: 0.0651
A6: CX100002 | B6: Metro | C6: 24 | D6: Y | E6: 29 | F6: 1 | G6: 7662.58 | H6: 0 | I6: 0 | J6: 0 | K6: 0 | L6: 0 | O6: 0 | P6: 2 | Q6: 58 | R6: 24 | S6: 0.91 | T6: 0 | U6: 0 | V6: 0.0569
A7: CX100003 | B7: Regional | C7: 55 | D7: Y | E7: 221 | F7: 3 | G7: 2847.11 | H7: 55876.4 | I7: 0 | J7: 0 | K7: 0 | L7: 0 | M7: 13800 | N7: 17.8 | O7: 923.15 | P7: 28 | Q7: 41 | R7: 7 | S7: 0.71 | T7: 0 | U7: 0 | V7: 0.032
A8: CX100004 | B8: Urban | C8: 86 | D8: N | E8: 353 | F8: 3 | G8: 16961.08 | H8: 0 | I8: 65900 | J8: 0 | K8: 0 | L8: 0 | M8: 19400 | N8: 64.9 | O8: 1183.39 | P8: 4 | Q8: 19 | R8: 0 | S8: 0.003 | T8: 0 | U8: 0 | V8: 0.0805
A9: CX100005 | B9: Regional | C9: 38 | D9: Y | E9: 120 | F9: 5 | G9: 1572.24 | H9: 23907.09 | I9: 14600 | J9: 0 | K9: 0 | L9: 15480 | O9: 0 | P9: 2 | Q9: 28 | R9: 8 | S9: 0.913 | T9: 0 | U9: 0 | V9: 0.0112
A10: CX100006 | B10: Urban | C10: 48 | D10: Y | E10: 173 | F10: 2 | G10: 363.89 | H10: 0 | I10: 0 | J10: 0 | K10: 0 | L10: 0 | O10: 0 | P10: 317 | Q10: 0 | R10: 0 | T10: 0 | U10: 0 | V10: 0.107
A11: CX100007 | B11: Urban | C11: 41 | D11: N | E11: 143 | F11: 3 | G11: 19854.9 | H11: 14388.09 | I11: 0 | J11: 0 | K11: 166400 | L11: 0 | O11: 0 | P11: 5 | Q11: 20 | R11: 12 | S11: 0.738 | T11: 1 | U11: 0 | V11: 0.2006
A12: CX100008 | B12: Metro | C12: 69 | D12: Y | E12: 223 | F12: 6 | G12: 4591.37 | H12: 9671.18 | I12: 47700 | J12: 34810.35 | K12: 124700 | L12: 0 | M12: 11300 | N12: 22.4 | O12: 773.2 | P12: 5 | Q12: 41 | R12: 0 | S12: 0.591 | T12: 0 | U12: 0 | V12: 0.0132
A13: CX100009 | B13: Regional | C13: 33 | D13: N | E13: 32 | F13: 4 | G13: 1942.02 | H13: 4187.7 | I13: 12000 | J13: 0 | K13: 0 | L13: 0 | M13: 3400 | N13: 17 | O13: 212.61 | P13: 18 | Q13: 27 | R13: 6 | S13: 0.575 | T13: 0 | U13: 0 | V13: 0.0419
A14: CX100010 | B14: Metro | C14: 43 | D14: Y | E14: 94 | F14: 4 | G14: 9811.04 | H14: 0 | I14: 0 | J14: 0 | K14: 0 | L14: 19280 | M14: 11800 | N14: 31.4 | O14: 467.38 | P14: 23 | Q14: 26 | R14: 7 | S14: 0.719 | T14: 0 | U14: 0 | V14: 0.0193
A15: CX100011 | B15: Regional | C15: 56 | D15: Y | E15: 65 | F15: 4 | G15: 6212.4 | H15: 59720.61 | I15: 0 | J15: 0 | K15: 238100 | L15: 0 | M15: 29600 | N15: 37 | O15: 527.48 | P15: 89 | Q15: 22 | R15: 7 | S15: 0.827 | T15: 0 | U15: 0 | V15: 0.0293
A16: CX100012 | B16: Regional | C16: 19 | D16: N | E16: 3 | F16: 2 | G16: 1016.59 | H16: 0 | I16: 0 | J16: 0 | K16: 0 | L16: 0 | M16: 1500 | N16: 50.4 | O16: 29.69 | P16: 0 | Q16: 16 | R16: 6 | S16: 0.928 | T16: 0 | U16: 0 | V16: 0.0822 | W16: region recoded
A17: CX100013 | B17: Urban | C17: 68 | D17: N | E17: 256 | F17: 5 | G17: 2057.21 | H17: 19460.2 | I17: 0 | J17: 19293.04 | K17: 0 | L17: 0 | M17: 3400 | N17: 20.9 | O17: 139.83 | P17: 11 | Q17: 41 | R17: 0 | S17: 0.354 | T17: 0 | U17: 0 | V17: 0.0326
A18: CX100014 | B18: Metro | C18: 40 | D18: Y | E18: 141 | F18: 3 | G18: 26458.34 | H18: 29362.2 | I18: 0 | J18: 0 | K18: 444000 | L18: 0 | O18: 0 | P18: 5 | Q18: 94 | R18: 0 | S18: 0.829 | T18: 0 | U18: 0 | V18: 0.0305 | W18: region recoded
A19: CX100015 | B19: Metro | C19: 72 | D19: Y | E19: 172 | F19: 3 | G19: 8693.63 | H19: 11051.58 | I19: 0 | J19: 0 | K19: 0 | L19: 0 | M19: 4000 | N19: 18.3 | O19: 365.95 | P19: 14 | Q19: 39 | R19: 7 | S19: 0.618 | T19: 1 | U19: 0 | V19: 0.0718
A20: CX100016 | B20: Metro | C20: 39 | D20: Y | E20: 147 | F20: 6 | G20: 9168.23 | H20: 37237.65 | I20: 106400 | J20: 340461.54 | K20: 165600 | L20: 0 | M20: 9800 | N20: 27.8 | O20: 840.73 | P20: 13 | Q20: 23 | R20: 10 | S20: 0.962 | T20: 1 | U20: 0 | V20: 0.0362
A21: CX100017 | B21: Metro | C21: 19 | D21: N | E21: 1 | F21: 4 | G21: 5340.67 | H21: 54203.16 | I21: 0 | J21: 0 | K21: 0 | L21: 19060 | M21: 14700 | N21: 49 | O21: 255.13 | P21: 9 | Q21: 16 | R21: 7 | S21: 0.822 | T21: 0 | U21: 0 | V21: 0.064
A22: CX100018 | B22: Regional | C22: 38 | D22: N | E22: 77 | F22: 2 | G22: 2378.47 | H22: 12705.46 | I22: 0 | J22: 0 | K22: 0 | L22: 0 | O22: 0 | P22: 7 | Q22: 13 | R22: 0 | S22: 0.601 | T22: 1 | U22: 0 | V22: 0.162
A23: CX100019 | B23: Regional | C23: 54 | D23: Y | E23: 31 | F23: 2 | G23: 4782.35 | H23: 0 | I23: 0 | J23: 0 | K23: 0 | L23: 0 | M23: 5700 | N23: 36.6 | O23: 2114.08 | P23: 4 | Q23: 44 | R23: 9 | S23: 0.469 | T23: 0 | U23: 0 | V23: 0.038
A24: CX100020 | B24: Metro | C24: 41 | D24: N | E24: 76 | F24: 2 | G24: 6253.63 | H24: 0 | I24: 0 | J24: 0 | K24: 0 | L24: 19470 | O24: 0 | P24: 78 | Q24: 16 | R24: 0 | S24: 0.926 | T24: 1 | U24: 1 | V24: 0.268
A25: CX100021 | B25: Metro | C25: 60 | D25: Y | E25: 353 | F25: 3 | G25: 11173.66 | H25: 1244520.6 | I25: 0 | J25: 0 | K25: 0 | L25: 0 | O25: 0 | P25: 4 | Q25: 25 | R25: 0 | S25: 0.815 | T25: 0 | U25: 0 | V25: 0.0245
A26: CX100022 | B26: Rural | C26: 54 | D26: N | E26: 257 | F26: 2 | G26: 8812.71 | H26: 141076.03 | I26: 0 | J26: 0 | K26: 0 | L26: 0 | O26: 0 | P26: 42 | Q26: 19 | R26: 0 | S26: 0.575 | T26: 2 | U26: 1 | V26: 0.3009
A27: CX100023 | B27: Metro | C27: 35 | D27: Y | E27: 40 | F27: 2 | G27: 5619.04 | H27: 0 | I27: 0 | J27: 0 | K27: 0 | L27: 0 | M27: 15500 | N27: 42.8 | O27: 105.81 | P27: 14 | Q27: 10 | R27: 9 | S27: 0.866 | T27: 0 | U27: 0 | V27: 0.0518
A28: CX100024 | B28: Rural | C28: 59 | D28: Y | E28: 304 | F28: 4 | G28: 3756.71 | H28: 9695.4 | I28: 25400 | J28: 0 | K28: 0 | L28: 0 | M28: 4400 | N28: 48.6 | O28: 667.9 | P28: 3 | Q28: 41 | R28: 0 | S28: 0.416 | T28: 0 | U28: 0 | V28: 0.0218
A29: CX100025 | B29: Regional | C29: 51 | D29: Y | F29: 3 | G29: 4446.39 | H29: 0 | I29: 0 | J29: 0 | K29: 0 | L29: 13470 | M29: 11300 | N29: 33 | O29: 233.66 | P29: 3 | Q29: 22 | R29: 9 | S29: 0.758 | T29: 0 | U29: 0 | V29: 0.027 | W29: tenure unknown
A30: CX100026 | B30: Metro | C30: 46 | D30: N | E30: 118 | F30: 4 | G30: 4720.81 | H30: 0 | I30: 0 | J30: 0 | K30: 40700 | L30: 20630 | M30: 1900 | N30: 31.9 | O30: 0 | P30: 155 | Q30: 0 | R30: 0 | T30: 0 | U30: 0 | V30: 0.2697
A31: CX100027 | B31: Metro | C31: 38 | D31: N | E31: 61 | F31: 5 | G31: 10822.81 | H31: 26338.4 | I31: 0 | J31: 513821.73 | K31: 475700 | L31: 0 | O31: 0 | P31: 20 | Q31: 14 | R31: 0 | S31: 0.961 | T31: 2 | U31: 1 | V31: 0.2769
A32: CX100028 | B32: Metro | C32: 34 | D32: N | E32: 127 | F32: 4 | G32: 819.88 | H32: 442.38 | I32: 5100 | J32: 0 | K32: 0 | L32: 0 | O32: 0 | P32: 222 | Q32: 0 | R32: 0 | T32: 0 | U32: 1 | V32: 0.1954
A33: CX100029 | B33: Urban | C33: 19 | D33: N | E33: 1 | F33: 3 | G33: 8625.56 | H33: 0 | I33: 0 | J33: 89906.71 | K33: 0 | L33: 0 | M33: 5300 | N33: 14.9 | O33: 61.85 | P33: 12 | Q33: 7 | R33: 7 | S33: 0.736 | T33: 0 | U33: 0 | V33: 0.165 | W33: num_products recalculated
A34: CX100030 | B34: Rural | C34: 65 | D34: Y | E34: 141 | F34: 4 | G34: 828.1 | H34: 17578.8 | I34: 34500 | J34: 0 | K34: 0 | L34: 0 | M34: 7800 | N34: 40.8 | O34: 0 | P34: 277 | Q34: 0 | R34: 0 | T34: 0 | U34: 0 | V34: 0.1139
A35: CX100031 | B35: Regional | C35: 56 | D35: Y | E35: 35 | F35: 5 | G35: 8581.29 | H35: 7763.48 | I35: 0 | J35: 121679.34 | K35: 190700 | L35: 0 | O35: 0 | P35: 4 | Q35: 35 | R35: 9 | S35: 0.474 | T35: 0 | U35: 0 | V35: 0.0128
A36: CX100032 | B36: Regional | C36: 63 | D36: Y | E36: 177 | F36: 2 | G36: 1416.48 | H36: 11844.88 | I36: 0 | J36: 0 | K36: 0 | L36: 0 | O36: 0 | P36: 5 | Q36: 44 | R36: 15 | S36: 0.49 | T36: 0 | U36: 0 | V36: 0.0183
A37: CX100033 | B37: Rural | C37: 38 | D37: N | E37: 15 | F37: 2 | G37: 4076.51 | H37: 43819.04 | I37: 0 | J37: 0 | K37: 0 | L37: 0 | O37: 0 | P37: 32 | Q37: 12 | R37: 2 | S37: 0.557 | T37: 0 | U37: 0 | V37: 0.092
A38: CX100034 | B38: Regional | C38: 56 | D38: N | E38: 21 | F38: 5 | G38: 2344.95 | H38: 32966.63 | I38: 120500 | J38: 0 | K38: 88900 | L38: 0 | M38: 14500 | N38: 35.5 | O38: 394.88 | P38: 21 | Q38: 19 | R38: 10 | S38: 0.918 | T38: 0 | U38: 0 | V38: 0.0541
A39: CX100035 | B39: Metro | C39: 33 | D39: Y | E39: 71 | F39: 3 | G39: 2588.22 | H39: 3500.82 | I39: 0 | J39: 0 | K39: 0 | L39: 23120 | O39: 0 | P39: 11 | Q39: 45 | R39: 15 | S39: 0.798 | T39: 0 | U39: 0 | V39: 0.0192
A40: CX100036 | B40: Rural | C40: 19 | D40: N | E40: 2 | F40: 1 | G40: 2237.82 | H40: 0 | I40: 0 | J40: 0 | K40: 0 | L40: 0 | O40: 0 | P40: 0 | Q40: 11 | R40: 9 | S40: 0.95 | T40: 1 | U40: 0 | V40: 0.1869
A41: CX100037 | B41: Regional | C41: 58 | D41: N | E41: 109 | F41: 3 | G41: 2139.68 | H41: 31754.71 | I41: 48100 | J41: 0 | K41: 0 | L41: 0 | O41: 0 | P41: 135 | Q41: 0 | R41: 0 | T41: 0 | U41: 1 | V41: 0.3072
A42: CX100038 | B42: Rural | C42: 55 | D42: N | E42: 58 | F42: 3 | G42: 7785.52 | H42: 0 | I42: 0 | J42: 0 | K42: 0 | L42: 13970 | M42: 12400 | N42: 31.8 | O42: 24.3 | P42: 82 | Q42: 6 | R42: 9 | S42: 0.618 | T42: 0 | U42: 0 | V42: 0.1229
A43: CX100039 | B43: Rural | C43: 63 | D43: Y | E43: 114 | F43: 3 | G43: 2844.71 | H43: 15939.36 | I43: 0 | J43: 0 | K43: 0 | L43: 0 | M43: 5000 | N43: 30.5 | O43: 610.71 | P43: 3 | Q43: 49 | R43: 0 | S43: 0.733 | T43: 0 | U43: 0 | V43: 0.0095
A44: CX100040 | B44: Urban | C44: 37 | D44: Y | E44: 47 | F44: 3 | G44: 2709.76 | H44: 2086.5 | I44: 0 | J44: 0 | K44: 0 | L44: 0 | M44: 3400 | N44: 4 | O44: 981.38 | P44: 5 | Q44: 49 | R44: 14 | S44: 0.52 | T44: 0 | U44: 0 | V44: 0.0246
A45: CX100041 | B45: Metro | C45: 70 | D45: Y | E45: 64 | F45: 1 | G45: 2123.26 | H45: 0 | I45: 0 | J45: 0 | K45: 0 | L45: 0 | O45: 0 | P45: 8 | Q45: 14 | R45: 0 | S45: 0.321 | T45: 0 | U45: 0 | V45: 0.0565
A46: CX100042 | B46: Rural | C46: 84 | D46: N | E46: 162 | F46: 3 | G46: 725.39 | H46: 0 | I46: 0 | J46: 0 | K46: 0 | L46: 25620 | M46: 5300 | N46: 26.5 | O46: 32.41 | P46: 12 | Q46: 15 | R46: 0 | S46: 0.314 | T46: 0 | U46: 0 | V46: 0.058 | W46: num_products recalculated
A47: CX100043 | B47: Rural | C47: 40 | D47: N | E47: 76 | F47: 3 | G47: 2391.03 | H47: 4351.5 | I47: 0 | J47: 0 | K47: 0 | L47: 0 | M47: 17700 | N47: 63.5 | O47: 354.42 | P47: 15 | Q47: 18 | R47: 3 | S47: 0.68 | T47: 0 | U47: 0 | V47: 0.0957
A48: CX100044 | B48: Metro | C48: 23 | D48: N | E48: 22 | F48: 4 | G48: 1319.34 | H48: 11847.72 | I48: 0 | J48: 0 | K48: 0 | L48: 14700 | M48: 4700 | N48: 51.1 | O48: 146.13 | P48: 25 | Q48: 31 | R48: 23 | S48: 1 | T48: 1 | U48: 0 | V48: 0.1137
A49: CX100045 | B49: Metro | C49: 22 | D49: N | E49: 5 | F49: 1 | G49: 388.5 | H49: 0 | I49: 0 | J49: 0 | K49: 0 | L49: 0 | O49: 0 | P49: 29 | Q49: 31 | R49: 16 | S49: 0.831 | T49: 0 | U49: 0 | V49: 0.0664
A50: CX100046 | B50: Rural | C50: 26 | D50: Y | E50: 34 | F50: 3 | G50: 2982.26 | H50: 0 | I50: 0 | J50: 0 | K50: 0 | L50: 0 | M50: 7600 | N50: 53.4 | O50: 535.82 | P50: 4 | Q50: 40 | R50: 16 | S50: 0.815 | T50: 0 | U50: 0 | V50: 0.029
A51: CX100047 | B51: Rural | C51: 38 | D51: Y | E51: 36 | F51: 2 | G51: 596.11 | H51: 1080.04 | I51: 0 | J51: 0 | K51: 0 | L51: 0 | O51: 0 | P51: 5 | Q51: 26 | R51: 5 | S51: 0.745 | T51: 1 | U51: 0 | V51: 0.059
A52: CX100048 | B52: Urban | C52: 59 | D52: Y | E52: 191 | F52: 3 | G52: 4783.12 | H52: 61081.31 | I52: 0 | J52: 0 | K52: 0 | L52: 0 | O52: 0 | P52: 2 | Q52: 41 | R52: 0 | S52: 0.572 | T52: 0 | U52: 0 | V52: 0.0242
A53: CX100049 | B53: Urban | C53: 66 | D53: N | E53: 10 | F53: 2 | G53: 122.96 | H53: 0 | I53: 0 | J53: 0 | K53: 0 | L53: 0 | O53: 0 | P53: 2 | Q53: 16 | R53: 0 | S53: 0.456 | T53: 0 | U53: 0 | V53: 0.0805
A54: CX100050 | B54: Regional | C54: 19 | D54: N | E54: 9 | F54: 2 | G54: 336.96 | H54: 0 | I54: 0 | J54: 0 | K54: 0 | L54: 0 | O54: 0 | P54: 4 | Q54: 13 | R54: 15 | S54: 0.912 | T54: 0 | U54: 0 | V54: 0.0994
A55: CX100051 | B55: Urban | C55: 35 | D55: Y | E55: 67 | F55: 3 | G55: 3660.84 | H55: 18608.14 | I55: 0 | J55: 27990.95 | K55: 0 | L55: 0 | O55: 0 | P55: 8 | Q55: 16 | R55: 9 | S55: 0.573 | T55: 1 | U55: 0 | V55: 0.048
A56: CX100052 | B56: Urban | C56: 25 | D56: Y | E56: 31 | F56: 2 | G56: 7822.56 | H56: 41004.19 | I56: 0 | J56: 0 | K56: 0 | L56: 0 | O56: 0 | P56: 5 | Q56: 49 | R56: 20 | S56: 0.806 | T56: 0 | U56: 0 | V56: 0.0403
A57: CX100053 | B57: Regional | C57: 46 | D57: N | E57: 159 | F57: 3 | G57: 2148.42 | H57: 9356.52 | I57: 0 | J57: 0 | K57: 0 | L57: 0 | O57: 0 | P57: 22 | Q57: 6 | R57: 4 | S57: 0.688 | T57: 1 | U57: 1 | V57: 0.2002
A58: CX100054 | B58: Metro | C58: 29 | D58: N | E58: 16 | F58: 2 | G58: 2699.63 | H58: 9740.28 | I58: 0 | J58: 0 | K58: 0 | L58: 0 | O58: 0 | P58: 22 | Q58: 7 | R58: 5 | S58: 0.791 | T58: 0 | U58: 0 | V58: 0.1952
A59: CX100055 | B59: Regional | C59: 59 | D59: Y | E59: 57 | F59: 3 | G59: 15565.34 | H59: 57007.32 | I59: 0 | J59: 0 | K59: 0 | L59: 0 | O59: 0 | P59: 24 | Q59: 48 | R59: 5 | S59: 0.436 | T59: 1 | U59: 0 | V59: 0.0415
A60: CX100056 | B60: Metro | C60: 38 | D60: Y | E60: 31 | F60: 2 | G60: 8917.19 | H60: 0 | I60: 0 | J60: 190884.08 | K60: 0 | L60: 0 | O60: 0 | P60: 1 | Q60: 176 | R60: 30 | S60: 0.732 | T60: 0 | U60: 0 | V60: 0.023
A61: CX100057 | B61: Regional | C61: 43 | D61: Y | E61: 71 | F61: 3 | G61: 3932.15 | H61: 4381.35 | I61: 0 | J61: 0 | K61: 0 | L61: 0 | M61: 7000 | N61: 23.3 | O61: 150.3 | P61: 2 | Q61: 33 | R61: 9 | S61: 0.606 | T61: 0 | U61: 0 | V61: 0.0235
A62: CX100058 | B62: Rural | C62: 32 | D62: N | E62: 62 | F62: 2 | G62: 3941.59 | H62: 8456.04 | I62: 0 | J62: 0 | K62: 0 | L62: 0 | O62: 0 | P62: 7 | Q62: 37 | R62: 12 | S62: 0.828 | T62: 0 | U62: 0 | V62: 0.0645
A63: CX100059 | B63: Regional | C63: 51 | D63: N | E63: 124 | F63: 6 | G63: 7589.71 | H63: 45041.47 | I63: 0 | J63: 43461.95 | K63: 221000 | L63: 0 | M63: 20900 | N63: 31.1 | O63: 0 | P63: 365 | Q63: 0 | R63: 0 | T63: 0 | U63: 0 | V63: 0.2881
A64: CX100060 | B64: Urban | C64: 53 | D64: N | E64: 182 | F64: 2 | G64: 1446.17 | H64: 0 | I64: 0 | J64: 0 | K64: 0 | L64: 0 | M64: 3200 | N64: 27.7 | O64: 0 | P64: 332 | Q64: 0 | R64: 0 | T64: 0 | U64: 0 | V64: 0.3082
A65: CX100061 | B65: Regional | C65: 46 | D65: Y | E65: 141 | F65: 4 | G65: 33239.21 | H65: 498299.89 | I65: 0 | J65: 0 | K65: 579600 | L65: 0 | M65: 23600 | N65: 31.7 | O65: 17225.22 | P65: 10 | Q65: 101 | R65: 8 | S65: 0.522 | T65: 1 | U65: 0 | V65: 0.0304
A66: CX100062 | B66: Regional | C66: 26 | D66: Y | E66: 40 | F66: 1 | G66: 1928.43 | H66: 0 | I66: 0 | J66: 0 | K66: 0 | L66: 0 | O66: 0 | P66: 5 | Q66: 21 | R66: 6 | S66: 0.965 | T66: 0 | U66: 1 | V66: 0.0671
A67: CX100063 | B67: Rural | C67: 70 | D67: Y | E67: 64 | F67: 4 | G67: 6538.56 | H67: 34420.17 | I67: 99100 | J67: 0 | K67: 0 | L67: 0 | M67: 12700 | N67: 23.9 | O67: 407.39 | P67: 60 | Q67: 40 | R67: 0 | S67: 0.293 | T67: 1 | U67: 0 | V67: 0.0519
A68: CX100064 | B68: Metro | C68: 33 | D68: N | E68: 52 | F68: 2 | G68: 10221.71 | H68: 28542.52 | I68: 0 | J68: 0 | K68: 0 | L68: 0 | O68: 0 | P68: 14 | Q68: 33 | R68: 13 | S68: 0.926 | T68: 0 | U68: 0 | V68: 0.0827
A69: CX100065 | B69: Metro | C69: 19 | D69: Y | E69: 4 | F69: 2 | G69: 4259.47 | H69: 23773.83 | I69: 0 | J69: 0 | K69: 0 | L69: 0 | O69: 0 | P69: 9 | Q69: 43 | R69: 0 | S69: 0.719 | T69: 1 | U69: 0 | V69: 0.0631
A70: CX100066 | B70: Urban | C70: 24 | D70: Y | E70: 23 | F70: 4 | G70: 415.19 | H70: 3953.59 | I70: 3400 | J70: 0 | K70: 0 | L70: 13870 | O70: 0 | P70: 4 | Q70: 23 | R70: 10 | S70: 0.781 | T70: 0 | U70: 0 | V70: 0.0288
A71: CX100067 | B71: Metro | C71: 33 | D71: Y | E71: 36 | F71: 3 | G71: 5897.32 | H71: 22697.83 | I71: 0 | J71: 0 | K71: 0 | L71: 15410 | O71: 0 | P71: 3 | Q71: 52 | R71: 0 | S71: 0.449 | T71: 0 | U71: 0 | V71: 0.0182
A72: CX100068 | B72: Regional | C72: 19 | D72: N | E72: 3 | F72: 2 | G72: 162.15 | H72: 0 | I72: 0 | J72: 0 | K72: 0 | L72: 0 | M72: 1000 | N72: 31.6 | O72: 0 | P72: 413 | Q72: 0 | R72: 0 | T72: 0 | U72: 1 | V72: 0.3343
A73: CX100069 | B73: Metro | C73: 58 | D73: N | E73: 32 | F73: 3 | G73: 12228.03 | H73: 0 | I73: 0 | J73: 0 | K73: 0 | L73: 0 | M73: 15500 | N73: 13.6 | O73: 357.19 | P73: 43 | Q73: 18 | R73: 0 | S73: 0.87 | T73: 0 | U73: 1 | V73: 0.1854
A74: CX100070 | B74: Rural | C74: 32 | D74: N | E74: 14 | F74: 3 | G74: 3737.06 | H74: 5038.23 | I74: 0 | J74: 0 | K74: 0 | L74: 0 | O74: 0 | P74: 22 | Q74: 17 | R74: 7 | S74: 0.816 | T74: 1 | U74: 0 | V74: 0.1779
A75: CX100071 | B75: Metro | C75: 31 | D75: Y | E75: 81 | F75: 2 | G75: 11478.53 | H75: 0 | I75: 0 | J75: 0 | K75: 0 | L75: 0 | O75: 0 | P75: 6 | Q75: 35 | R75: 11 | S75: 1 | T75: 0 | U75: 0 | V75: 0.0217
A76: CX100072 | B76: Rural | C76: 38 | D76: N | E76: 19 | F76: 1 | G76: 5085.09 | H76: 0 | I76: 0 | J76: 0 | K76: 0 | L76: 0 | O76: 0 | P76: 40 | Q76: 19 | R76: 10 | S76: 0.378 | T76: 0 | U76: 0 | V76: 0.1514
A77: CX100073 | B77: Urban | C77: 76 | D77: Y | E77: 289 | F77: 3 | G77: 2229.75 | H77: 20155.64 | I77: 0 | J77: 55816.48 | K77: 0 | L77: 0 | O77: 0 | P77: 9 | Q77: 37 | R77: 4 | S77: 0.126 | T77: 0 | U77: 0 | V77: 0.0173
A78: CX100074 | B78: Urban | C78: 46 | D78: N | E78: 104 | F78: 5 | G78: 8644.53 | H78: 18914.02 | I78: 0 | J78: 0 | K78: 375000 | L78: 0 | M78: 16700 | N78: 42 | O78: 696.58 | P78: 4 | Q78: 18 | R78: 9 | S78: 0.769 | T78: 1 | U78: 0 | V78: 0.1534
A79: CX100075 | B79: Metro | C79: 42 | D79: N | E79: 38 | F79: 6 | G79: 12612.47 | H79: 33101.88 | I79: 19100 | J79: 0 | K79: 286800 | L79: 13530 | M79: 21500 | N79: 38 | O79: 1547.34 | P79: 4 | Q79: 42 | R79: 22 | S79: 0.923 | T79: 0 | U79: 0 | V79: 0.0446
A80: CX100076 | B80: Regional | C80: 63 | D80: N | E80: 298 | F80: 2 | G80: 4278.12 | H80: 11281.86 | I80: 0 | J80: 0 | K80: 0 | L80: 0 | O80: 0 | P80: 5 | Q80: 29 | R80: 10 | S80: 0.67 | T80: 0 | U80: 0 | V80: 0.0629
A81: CX100077 | B81: Urban | C81: 27 | D81: N | E81: 42 | F81: 3 | G81: 5961.51 | H81: 0 | I81: 0 | J81: 0 | K81: 0 | L81: 1850 | M81: 15200 | N81: 21.5 | O81: 520.98 | P81: 2 | Q81: 22 | R81: 10 | S81: 0.87 | T81: 0 | U81: 0 | V81: 0.0552
A82: CX100078 | B82: Urban | C82: 32 | D82: Y | E82: 68 | F82: 2 | G82: 13556.96 | H82: 0 | I82: 0 | J82: 0 | K82: 204100 | L82: 0 | O82: 0 | P82: 3 | Q82: 16 | R82: 8 | S82: 0.973 | T82: 0 | U82: 0 | V82: 0.0417
A83: CX100079 | B83: Metro | C83: 60 | D83: N | E83: 347 | F83: 5 | G83: 6455.78 | H83: 147231.74 | I83: 218600 | J83: 2287200 | K83: 0 | L83: 0 | M83: 40000 | N83: 43.1 | O83: 0 | P83: 106 | Q83: 0 | R83: 3 | T83: 0 | U83: 0 | V83: 0.1441
A84: CX100080 | B84: Rural | C84: 50 | D84: Y | E84: 30 | F84: 3 | G84: 6613.9 | H84: 0 | I84: 0 | J84: 0 | K84: 102700 | L84: 0 | M84: 14700 | N84: 37.1 | O84: 920.69 | P84: 10 | Q84: 60 | R84: 9 | S84: 0.685 | T84: 1 | U84: 0 | V84: 0.0399
A85: CX100081 | B85: Metro | C85: 40 | D85: N | E85: 178 | F85: 3 | G85: 1672.36 | H85: 0 | I85: 0 | J85: 0 | K85: 159600 | L85: 0 | O85: 0 | P85: 187 | Q85: 0 | R85: 0 | T85: 2 | U85: 0 | V85: 0.5909
A86: CX100082 | B86: Urban | C86: 69 | D86: Y | E86: 456 | F86: 5 | G86: 2603.07 | H86: 21923.66 | I86: 50900 | J86: 160955.4 | K86: 0 | L86: 0 | M86: 6200 | N86: 17.1 | O86: 535.96 | P86: 6 | Q86: 36 | R86: 10 | S86: 0.591 | T86: 1 | U86: 0 | V86: 0.0211
A87: CX100083 | B87: Rural | C87: 77 | D87: N | E87: 279 | F87: 4 | G87: 2482.25 | H87: 55539.31 | I87: 23200 | J87: 0 | K87: 0 | L87: 0 | M87: 7400 | N87: 10.5 | O87: 667.6 | P87: 3 | Q87: 24 | R87: 0 | S87: 0.134 | T87: 0 | U87: 0 | V87: 0.0636
A88: CX100084 | B88: Rural | C88: 26 | D88: Y | E88: 38 | F88: 4 | G88: 5323.1 | H88: 84143.17 | I88: 121600 | J88: 0 | K88: 0 | L88: 0 | M88: 16700 | N88: 51.3 | O88: 1088.42 | P88: 0 | Q88: 37 | R88: 9 | S88: 0.821 | T88: 3 | U88: 0 | V88: 0.1065
A89: CX100085 | B89: Metro | C89: 41 | D89: Y | E89: 62 | F89: 3 | G89: 7390.79 | H89: 0 | I89: 0 | J89: 0 | K89: 167700 | L89: 1780 | O89: 0 | P89: 66 | Q89: 24 | R89: 9 | S89: 0.65 | T89: 1 | U89: 0 | V89: 0.1033
A90: CX100086 | B90: Metro | C90: 44 | D90: Y | E90: 84 | F90: 3 | G90: 5874.78 | H90: 0 | I90: 93400 | J90: 0 | K90: 0 | L90: 0 | M90: 17400 | N90: 7 | O90: 812.7 | P90: 1 | Q90: 85 | R90: 20 | S90: 0.755 | T90: 0 | U90: 0 | V90: 0.0203
A91: CX100087 | B91: Urban | C91: 46 | D91: Y | E91: 93 | F91: 2 | G91: 10315.7 | H91: 13400.04 | I91: 0 | J91: 0 | K91: 0 | L91: 0 | O91: 0 | P91: 6 | Q91: 78 | R91: 8 | S91: 0.643 | T91: 0 | U91: 0 | V91: 0.0239
A92: CX100088 | B92: Urban | C92: 20 | D92: N | E92: 1 | F92: 3 | G92: 3959.71 | H92: 15442.63 | I92: 0 | J92: 0 | K92: 0 | L92: 0 | M92: 8700 | N92: 55.7 | O92: 0 | P92: 199 | Q92: 0 | R92: 0 | T92: 0 | U92: 1 | V92: 0.2905
A93: CX100089 | B93: Metro | C93: 50 | D93: N | E93: 106 | F93: 4 | G93: 8549.74 | H93: 6832.35 | I93: 53300 | J93: 0 | K93: 0 | L93: 0 | O93: 0 | P93: 11 | Q93: 23 | R93: 3 | S93: 0.483 | T93: 0 | U93: 0 | V93: 0.0468 | W93: region recoded
A94: CX100090 | B94: Regional | C94: 20 | D94: Y | E94: 4 | F94: 2 | G94: 1048.59 | H94: 0 | I94: 0 | J94: 0 | K94: 0 | L94: 17630 | O94: 0 | P94: 2 | Q94: 28 | R94: 0 | S94: 0.902 | T94: 0 | U94: 0 | V94: 0.0473
A95: CX100091 | B95: Urban | C95: 52 | D95: Y | E95: 4 | F95: 5 | G95: 4640.54 | H95: 12043.94 | I95: 0 | J95: 78307.03 | K95: 0 | L95: 8780 | M95: 14700 | N95: 36.4 | O95: 231.35 | P95: 3 | Q95: 31 | R95: 10 | S95: 0.628 | T95: 0 | U95: 0 | V95: 0.0218
A96: CX100092 | B96: Metro | C96: 52 | D96: Y | E96: 74 | F96: 3 | G96: 22682.1 | H96: 479688.38 | I96: 0 | J96: 0 | K96: 0 | L96: 0 | M96: 31100 | N96: 8.5 | O96: 5247.58 | P96: 6 | Q96: 85 | R96: 13 | S96: 0.654 | T96: 1 | U96: 0 | V96: 0.0547
A97: CX100093 | B97: Rural | C97: 54 | D97: Y | E97: 205 | F97: 5 | G97: 1280.25 | H97: 8544.33 | I97: 0 | J97: 12186.39 | K97: 20600 | L97: 0 | O97: 0 | P97: 362 | Q97: 0 | R97: 0 | T97: 0 | U97: 0 | V97: 0.0764
A98: CX100094 | B98: Urban | C98: 40 | D98: Y | E98: 31 | F98: 1 | G98: 16032.36 | H98: 0 | I98: 0 | J98: 0 | K98: 0 | L98: 0 | O98: 0 | P98: 33 | Q98: 13 | R98: 9 | S98: 0.893 | T98: 0 | U98: 0 | V98: 0.0683
A99: CX100095 | B99: Rural | C99: 72 | D99: N | E99: 113 | F99: 2 | G99: 1617.15 | H99: 0 | I99: 27700 | J99: 0 | K99: 0 | L99: 0 | O99: 0 | P99: 27 | Q99: 14 | R99: 7 | S99: 0.304 | T99: 0 | U99: 1 | V99: 0.1288
A100: CX100096 | B100: Metro | C100: 19 | D100: Y | E100: 10 | F100: 5 | G100: 1301.48 | H100: 7228.13 | I100: 0 | J100: 0 | K100: 0 | L100: 21250 | M100: 3700 | N100: 15.5 | O100: 324.03 | P100: 11 | Q100: 56 | R100: 21 | S100: 0.714 | T100: 1 | U100: 0 | V100: 0.0268
A101: CX100097 | B101: Metro | C101: 35 | D101: Y | E101: 107 | F101: 3 | G101: 8073.4 | H101: 11429.71 | I101: 0 | J101: 0 | K101: 0 | L101: 0 | M101: 14900 | N101: 24.7 | O101: 2088.34 | P101: 8 | Q101: 79 | R101: 22 | S101: 0.877 | T101: 0 | U101: 0 | V101: 0.03
...

Sheet Scoring
A1: Scoring – live formulas
A2: Green = pulled from Data_Clean · black = calculated from Assumptions
A4: customer_id | B4: rev_current_account | C4: rev_savings | D4: rev_term_deposit | E4: rev_investments | F4: rev_mortgage | G4: rev_personal_loan | H4: rev_card_revolve | I4: rev_card_interchange | J4: est_annual_revenue | K4: rei_recency | L4: rei_frequency | M4: rei_digital | N4: rei_adoption | O4: rei_loyalty | P4: rei | Q4: value_band | R4: engagement_band | S4: segment | T4: expected_revenue_at_risk
A5: =Data_Clean!A5 -> CX100001 | B5: =Data_Clean!G5*Assumptions!$B$5 -> 103.33225 | C5: =IF(Data_Clean!H5="",0,Data_Clean!H5)*Assumptions!$B$6 -> 0 | D5: =Data_Clean!I5*Assumptions!$B$7 -> 0 | E5: =Data_Clean!J5*Assumptions!$B$8 -> 296.58533 | F5: =Data_Clean!K5*Assumptions!$B$9 -> 0 | G5: =Data_Clean!L5*Assumptions!$B$10 -> 0 | H5: =IF(OR(Data_Clean!M5="",Data_Clean!N5=""),0,Data_Clean!M5*Data_Clean!N5/100)*Assumptions!$B$13*Assumptions!$B$11 -> 392.268 | I5: =Data_Clean!O5*4*Assumptions!$B$12 -> 11.24688 | J5: =SUM(B5:I5) -> 803.43246 | K5: =IF(Data_Clean!P5="","",Assumptions!$B$15*0.5^(Data_Clean!P5/Assumptions!$B$20)) -> 30 | L5: =Assumptions!$B$16*MIN(1,LN(1+Data_Clean!Q5)/LN(1+Assumptions!$B$21)) -> 13.744707 | M5: =Assumptions!$B$17*(0.6*MIN(1,Data_Clean!R5/Assumptions!$B$22)+0.4*IF(Data_Clean!S5="",0,Data_Clean!S5)) -> 9.288 | N5: =Assumptions!$B$18*MIN(1,(Data_Clean!F5-1)/Assumptions!$B$23) -> 10 | O5: =Assumptions!$B$19*(0.4*IF(Data_Clean!E5="",0,MIN(1,Data_Clean!E5/12/Assumptions!$B$24))+0.35*IF(Data_Clean!D5="Y",1,0)+0.25*(1-MIN(Data_Clean!T5,3)/3))/IF(Data_Clean!E5="",0.6,1) -> 5.9 | P5: =SUM(K5:O5)/(Assumptions!$D$5-IF(K5="",Assumptions!$B$15,0))*100 -> 68.932707 | Q5: =IF(J5>=Assumptions!$B$26,"High",IF(J5>=Assumptions!$B$27,"Mid","Low")) -> Mid | R5: =IF(P5>=Assumptions!$B$28,"High",IF(P5>=Assumptions!$B$29,"Mid","Low")) -> Mid | S5: =INDEX(Assumptions!$B$33:$B$41,MATCH(Q5&"|"&R5,Assumptions!$A$33:$A$41,0)) -> Established Core | T5: =IF(ISNUMBER(Data_Clean!V5),J5*Data_Clean!V5,0) -> 52.303453
A6: =Data_Clean!A6 -> CX100002 | B6: =Data_Clean!G6*Assumptions!$B$5 -> 191.5645 | C6: =IF(Data_Clean!H6="",0,Data_Clean!H6)*Assumptions!$B$6 -> 0 | D6: =Data_Clean!I6*Assumptions!$B$7 -> 0 | E6: =Data_Clean!J6*Assumptions!$B$8 -> 0 | F6: =Data_Clean!K6*Assumptions!$B$9 -> 0 | G6: =Data_Clean!L6*Assumptions!$B$10 -> 0 | H6: =IF(OR(Data_Clean!M6="",Data_Clean!N6=""),0,Data_Clean!M6*Data_Clean!N6/100)*Assumptions!$B$13*Assumptions!$B$11 -> 0 | I6: =Data_Clean!O6*4*Assumptions!$B$12 -> 0 | J6: =SUM(B6:I6) -> 191.5645 | K6: =IF(Data_Clean!P6="","",Assumptions!$B$15*0.5^(Data_Clean!P6/Assumptions!$B$20)) -> 28.645248 | L6: =Assumptions!$B$16*MIN(1,LN(1+Data_Clean!Q6)/LN(1+Assumptions!$B$21)) -> 17.004652 | M6: =Assumptions!$B$17*(0.6*MIN(1,Data_Clean!R6/Assumptions!$B$22)+0.4*IF(Data_Clean!S6="",0,Data_Clean!S6)) -> 14.46 | N6: =Assumptions!$B$18*MIN(1,(Data_Clean!F6-1)/Assumptions!$B$23) -> 0 | O6: =Assumptions!$B$19*(0.4*IF(Data_Clean!E6="",0,MIN(1,Data_Clean!E6/12/Assumptions!$B$24))+0.35*IF(Data_Clean!D6="Y",1,0)+0.25*(1-MIN(Data_Clean!T6,3)/3))/IF(Data_Clean!E6="",0.6,1) -> 10.45 | P6: =SUM(K6:O6)/(Assumptions!$D$5-IF(K6="",Assumptions!$B$15,0))*100 -> 70.5599 | Q6: =IF(J6>=Assumptions!$B$26,"High",IF(J6>=Assumptions!$B$27,"Mid","Low")) -> Low | R6: =IF(P6>=Assumptions!$B$28,"High",IF(P6>=Assumptions!$B$29,"Mid","Low")) -> High | S6: =INDEX(Assumptions!$B$33:$B$41,MATCH(Q6&"|"&R6,Assumptions!$A$33:$A$41,0)) -> Engaged Builders | T6: =IF(ISNUMBER(Data_Clean!V6),J6*Data_Clean!V6,0) -> 10.90002
A7: =Data_Clean!A7 -> CX100003 | B7: =Data_Clean!G7*Assumptions!$B$5 -> 71.17775 | C7: =IF(Data_Clean!H7="",0,Data_Clean!H7)*Assumptions!$B$6 -> 670.5168 | D7: =Data_Clean!I7*Assumptions!$B$7 -> 0 | E7: =Data_Clean!J7*Assumptions!$B$8 -> 0 | F7: =Data_Clean!K7*Assumptions!$B$9 -> 0 | G7: =Data_Clean!L7*Assumptions!$B$10 -> 0 | H7: =IF(OR(Data_Clean!M7="",Data_Clean!N7=""),0,Data_Clean!M7*Data_Clean!N7/100)*Assumptions!$B$13*Assumptions!$B$11 -> 147.384 | I7: =Data_Clean!O7*4*Assumptions!$B$12 -> 44.3112 | J7: =SUM(B7:I7) -> 933.38975 | K7: =IF(Data_Clean!P7="","",Assumptions!$B$15*0.5^(Data_Clean!P7/Assumptions!$B$20)) -> 15.709412 | L7: =Assumptions!$B$16*MIN(1,LN(1+Data_Clean!Q7)/LN(1+Assumptions!$B$21)) -> 15.587293 | M7: =Assumptions!$B$17*(0.6*MIN(1,Data_Clean!R7/Assumptions!$B$22)+0.4*IF(Data_Clean!S7="",0,Data_Clean!S7)) -> 7.41 | N7: =Assumptions!$B$18*MIN(1,(Data_Clean!F7-1)/Assumptions!$B$23) -> 10 | O7: =Assumptions!$B$19*(0.4*IF(Data_Clean!E7="",0,MIN(1,Data_Clean!E7/12/Assumptions!$B$24))+0.35*IF(Data_Clean!D7="Y",1,0)+0.25*(1-MIN(Data_Clean!T7,3)/3))/IF(Data_Clean!E7="",0.6,1) -> 15 | P7: =SUM(K7:O7)/(Assumptions!$D$5-IF(K7="",Assumptions!$B$15,0))*100 -> 63.706705 | Q7: =IF(J7>=Assumptions!$B$26,"High",IF(J7>=Assumptions!$B$27,"Mid","Low")) -> Mid | R7: =IF(P7>=Assumptions!$B$28,"High",IF(P7>=Assumptions!$B$29,"Mid","Low")) -> Mid | S7: =INDEX(Assumptions!$B$33:$B$41,MATCH(Q7&"|"&R7,Assumptions!$A$33:$A$41,0)) -> Established Core | T7: =IF(ISNUMBER(Data_Clean!V7),J7*Data_Clean!V7,0) -> 29.868472
A8: =Data_Clean!A8 -> CX100004 | B8: =Data_Clean!G8*Assumptions!$B$5 -> 424.027 | C8: =IF(Data_Clean!H8="",0,Data_Clean!H8)*Assumptions!$B$6 -> 0 | D8: =Data_Clean!I8*Assumptions!$B$7 -> 527.2 | E8: =Data_Clean!J8*Assumptions!$B$8 -> 0 | F8: =Data_Clean!K8*Assumptions!$B$9 -> 0 | G8: =Data_Clean!L8*Assumptions!$B$10 -> 0 | H8: =IF(OR(Data_Clean!M8="",Data_Clean!N8=""),0,Data_Clean!M8*Data_Clean!N8/100)*Assumptions!$B$13*Assumptions!$B$11 -> 755.436 | I8: =Data_Clean!O8*4*Assumptions!$B$12 -> 56.80272 | J8: =SUM(B8:I8) -> 1763.4657 | K8: =IF(Data_Clean!P8="","",Assumptions!$B$15*0.5^(Data_Clean!P8/Assumptions!$B$20)) -> 27.351675 | L8: =Assumptions!$B$16*MIN(1,LN(1+Data_Clean!Q8)/LN(1+Assumptions!$B$21)) -> 12.493174 | M8: =Assumptions!$B$17*(0.6*MIN(1,Data_Clean!R8/Assumptions!$B$22)+0.4*IF(Data_Clean!S8="",0,Data_Clean!S8)) -> 0.018 | N8: =Assumptions!$B$18*MIN(1,(Data_Clean!F8-1)/Assumptions!$B$23) -> 10 | O8: =Assumptions!$B$19*(0.4*IF(Data_Clean!E8="",0,MIN(1,Data_Clean!E8/12/Assumptions!$B$24))+0.35*IF(Data_Clean!D8="Y",1,0)+0.25*(1-MIN(Data_Clean!T8,3)/3))/IF(Data_Clean!E8="",0.6,1) -> 9.75 | P8: =SUM(K8:O8)/(Assumptions!$D$5-IF(K8="",Assumptions!$B$15,0))*100 -> 59.612849 | Q8: =IF(J8>=Assumptions!$B$26,"High",IF(J8>=Assumptions!$B$27,"Mid","Low")) -> High | R8: =IF(P8>=Assumptions!$B$28,"High",IF(P8>=Assumptions!$B$29,"Mid","Low")) -> Mid | S8: =INDEX(Assumptions!$B$33:$B$41,MATCH(Q8&"|"&R8,Assumptions!$A$33:$A$41,0)) -> Established Core | T8: =IF(ISNUMBER(Data_Clean!V8),J8*Data_Clean!V8,0) -> 141.95899
A9: =Data_Clean!A9 -> CX100005 | B9: =Data_Clean!G9*Assumptions!$B$5 -> 39.306 | C9: =IF(Data_Clean!H9="",0,Data_Clean!H9)*Assumptions!$B$6 -> 286.88508 | D9: =Data_Clean!I9*Assumptions!$B$7 -> 116.8 | E9: =Data_Clean!J9*Assumptions!$B$8 -> 0 | F9: =Data_Clean!K9*Assumptions!$B$9 -> 0 | G9: =Data_Clean!L9*Assumptions!$B$10 -> 696.6 | H9: =IF(OR(Data_Clean!M9="",Data_Clean!N9=""),0,Data_Clean!M9*Data_Clean!N9/100)*Assumptions!$B$13*Assumptions!$B$11 -> 0 | I9: =Data_Clean!O9*4*Assumptions!$B$12 -> 0 | J9: =SUM(B9:I9) -> 1139.5911 | K9: =IF(Data_Clean!P9="","",Assumptions!$B$15*0.5^(Data_Clean!P9/Assumptions!$B$20)) -> 28.645248 | L9: =Assumptions!$B$16*MIN(1,LN(1+Data_Clean!Q9)/LN(1+Assumptions!$B$21)) -> 14.042714 | M9: =Assumptions!$B$17*(0.6*MIN(1,Data_Clean!R9/Assumptions!$B$22)+0.4*IF(Data_Clean!S9="",0,Data_Clean!S9)) -> 9.078 | N9: =Assumptions!$B$18*MIN(1,(Data_Clean!F9-1)/Assumptions!$B$23) -> 20 | O9: =Assumptions!$B$19*(0.4*IF(Data_Clean!E9="",0,MIN(1,Data_Clean!E9/12/Assumptions!$B$24))+0.35*IF(Data_Clean!D9="Y",1,0)+0.25*(1-MIN(Data_Clean!T9,3)/3))/IF(Data_Clean!E9="",0.6,1) -> 15 | P9: =SUM(K9:O9)/(Assumptions!$D$5-IF(K9="",Assumptions!$B$15,0))*100 -> 86.765962 | Q9: =IF(J9>=Assumptions!$B$26,"High",IF(J9>=Assumptions!$B$27,"Mid","Low")) -> Mid | R9: =IF(P9>=Assumptions!$B$28,"High",IF(P9>=Assumptions!$B$29,"Mid","Low")) -> High | S9: =INDEX(Assumptions!$B$33:$B$41,MATCH(Q9&"|"&R9,Assumptions!$A$33:$A$41,0)) -> Engaged Builders | T9: =IF(ISNUMBER(Data_Clean!V9),J9*Data_Clean!V9,0) -> 12.76342
A10: =Data_Clean!A10 -> CX100006 | B10: =Data_Clean!G10*Assumptions!$B$5 -> 9.09725 | C10: =IF(Data_Clean!H10="",0,Data_Clean!H10)*Assumptions!$B$6 -> 0 | D10: =Data_Clean!I10*Assumptions!$B$7 -> 0 | E10: =Data_Clean!J10*Assumptions!$B$8 -> 0 | F10: =Data_Clean!K10*Assumptions!$B$9 -> 0 | G10: =Data_Clean!L10*Assumptions!$B$10 -> 0 | H10: =IF(OR(Data_Clean!M10="",Data_Clean!N10=""),0,Data_Clean!M10*Data_Clean!N10/100)*Assumptions!$B$13*Assumptions!$B$11 -> 0 | I10: =Data_Clean!O10*4*Assumptions!$B$12 -> 0 | J10: =SUM(B10:I10) -> 9.09725 | K10: =IF(Data_Clean!P10="","",Assumptions!$B$15*0.5^(Data_Clean!P10/Assumptions!$B$20)) -> 0.019780517 | L10: =Assumptions!$B$16*MIN(1,LN(1+Data_Clean!Q10)/LN(1+Assumptions!$B$21)) -> 0 | M10: =Assumptions!$B$17*(0.6*MIN(1,Data_Clean!R10/Assumptions!$B$22)+0.4*IF(Data_Clean!S10="",0,Data_Clean!S10)) -> 0 | N10: =Assumptions!$B$18*MIN(1,(Data_Clean!F10-1)/Assumptions!$B$23) -> 5 | O10: =Assumptions!$B$19*(0.4*IF(Data_Clean!E10="",0,MIN(1,Data_Clean!E10/12/Assumptions!$B$24))+0.35*IF(Data_Clean!D10="Y",1,0)+0.25*(1-MIN(Data_Clean!T10,3)/3))/IF(Data_Clean!E10="",0.6,1) -> 15 | P10: =SUM(K10:O10)/(Assumptions!$D$5-IF(K10="",Assumptions!$B$15,0))*100 -> 20.019781 | Q10: =IF(J10>=Assumptions!$B$26,"High",IF(J10>=Assumptions!$B$27,"Mid","Low")) -> Low | R10: =IF(P10>=Assumptions!$B$28,"High",IF(P10>=Assumptions!$B$29,"Mid","Low")) -> Low | S10: =INDEX(Assumptions!$B$33:$B$41,MATCH(Q10&"|"&R10,Assumptions!$A$33:$A$41,0)) -> Dormant & Low Value | T10: =IF(ISNUMBER(Data_Clean!V10),J10*Data_Clean!V10,0) -> 0.97340575
A11: =Data_Clean!A11 -> CX100007 | B11: =Data_Clean!G11*Assumptions!$B$5 -> 496.3725 | C11: =IF(Data_Clean!H11="",0,Data_Clean!H11)*Assumptions!$B$6 -> 172.65708 | D11: =Data_Clean!I11*Assumptions!$B$7 -> 0 | E11: =Data_Clean!J11*Assumptions!$B$8 -> 0 | F11: =Data_Clean!K11*Assumptions!$B$9 -> 1830.4 | G11: =Data_Clean!L11*Assumptions!$B$10 -> 0 | H11: =IF(OR(Data_Clean!M11="",Data_Clean!N11=""),0,Data_Clean!M11*Data_Clean!N11/100)*Assumptions!$B$13*Assumptions!$B$11 -> 0 | I11: =Data_Clean!O11*4*Assumptions!$B$12 -> 0 | J11: =SUM(B11:I11) -> 2499.4296 | K11: =IF(Data_Clean!P11="","",Assumptions!$B$15*0.5^(Data_Clean!P11/Assumptions!$B$20)) -> 26.726962 | L11: =Assumptions!$B$16*MIN(1,LN(1+Data_Clean!Q11)/LN(1+Assumptions!$B$21)) -> 12.696645 | M11: =Assumptions!$B$17*(0.6*MIN(1,Data_Clean!R11/Assumptions!$B$22)+0.4*IF(Data_Clean!S11="",0,Data_Clean!S11)) -> 9.828 | N11: =Assumptions!$B$18*MIN(1,(Data_Clean!F11-1)/Assumptions!$B$23) -> 10 | O11: =Assumptions!$B$19*(0.4*IF(Data_Clean!E11="",0,MIN(1,Data_Clean!E11/12/Assumptions!$B$24))+0.35*IF(Data_Clean!D11="Y",1,0)+0.25*(1-MIN(Data_Clean!T11,3)/3))/IF(Data_Clean!E11="",0.6,1) -> 8.5 | P11: =SUM(K11:O11)/(Assumptions!$D$5-IF(K11="",Assumptions!$B$15,0))*100 -> 67.751606 | Q11: =IF(J11>=Assumptions!$B$26,"High",IF(J11>=Assumptions!$B$27,"Mid","Low")) -> High | R11: =IF(P11>=Assumptions!$B$28,"High",IF(P11>=Assumptions!$B$29,"Mid","Low")) -> Mid | S11: =INDEX(Assumptions!$B$33:$B$41,MATCH(Q11&"|"&R11,Assumptions!$A$33:$A$41,0)) -> Established Core | T11: =IF(ISNUMBER(Data_Clean!V11),J11*Data_Clean!V11,0) -> 501.38557
A12: =Data_Clean!A12 -> CX100008 | B12: =Data_Clean!G12*Assumptions!$B$5 -> 114.78425 | C12: =IF(Data_Clean!H12="",0,Data_Clean!H12)*Assumptions!$B$6 -> 116.05416 | D12: =Data_Clean!I12*Assumptions!$B$7 -> 381.6 | E12: =Data_Clean!J12*Assumptions!$B$8 -> 261.07763 | F12: =Data_Clean!K12*Assumptions!$B$9 -> 1371.7 | G12: =Data_Clean!L12*Assumptions!$B$10 -> 0 | H12: =IF(OR(Data_Clean!M12="",Data_Clean!N12=""),0,Data_Clean!M12*Data_Clean!N12/100)*Assumptions!$B$13*Assumptions!$B$11 -> 151.872 | I12: =Data_Clean!O12*4*Assumptions!$B$12 -> 37.1136 | J12: =SUM(B12:I12) -> 2434.2016 | K12: =IF(Data_Clean!P12="","",Assumptions!$B$15*0.5^(Data_Clean!P12/Assumptions!$B$20)) -> 26.726962 | L12: =Assumptions!$B$16*MIN(1,LN(1+Data_Clean!Q12)/LN(1+Assumptions!$B$21)) -> 15.587293 | M12: =Assumptions!$B$17*(0.6*MIN(1,Data_Clean!R12/Assumptions!$B$22)+0.4*IF(Data_Clean!S12="",0,Data_Clean!S12)) -> 3.546 | N12: =Assumptions!$B$18*MIN(1,(Data_Clean!F12-1)/Assumptions!$B$23) -> 20 | O12: =Assumptions!$B$19*(0.4*IF(Data_Clean!E12="",0,MIN(1,Data_Clean!E12/12/Assumptions!$B$24))+0.35*IF(Data_Clean!D12="Y",1,0)+0.25*(1-MIN(Data_Clean!T12,3)/3))/IF(Data_Clean!E12="",0.6,1) -> 15 | P12: =SUM(K12:O12)/(Assumptions!$D$5-IF(K12="",Assumptions!$B$15,0))*100 -> 80.860255 | Q12: =IF(J12>=Assumptions!$B$26,"High",IF(J12>=Assumptions!$B$27,"Mid","Low")) -> High | R12: =IF(P12>=Assumptions!$B$28,"High",IF(P12>=Assumptions!$B$29,"Mid","Low")) -> High | S12: =INDEX(Assumptions!$B$33:$B$41,MATCH(Q12&"|"&R12,Assumptions!$A$33:$A$41,0)) -> Premier Advocates | T12: =IF(ISNUMBER(Data_Clean!V12),J12*Data_Clean!V12,0) -> 32.131462
A13: =Data_Clean!A13 -> CX100009 | B13: =Data_Clean!G13*Assumptions!$B$5 -> 48.5505 | C13: =IF(Data_Clean!H13="",0,Data_Clean!H13)*Assumptions!$B$6 -> 50.2524 | D13: =Data_Clean!I13*Assumptions!$B$7 -> 96 | E13: =Data_Clean!J13*Assumptions!$B$8 -> 0 | F13: =Data_Clean!K13*Assumptions!$B$9 -> 0 | G13: =Data_Clean!L13*Assumptions!$B$10 -> 0 | H13: =IF(OR(Data_Clean!M13="",Data_Clean!N13=""),0,Data_Clean!M13*Data_Clean!N13/100)*Assumptions!$B$13*Assumptions!$B$11 -> 34.68 | I13: =Data_Clean!O13*4*Assumptions!$B$12 -> 10.20528 | J13: =SUM(B13:I13) -> 239.68818 | K13: =IF(Data_Clean!P13="","",Assumptions!$B$15*0.5^(Data_Clean!P13/Assumptions!$B$20)) -> 19.792619 | L13: =Assumptions!$B$16*MIN(1,LN(1+Data_Clean!Q13)/LN(1+Assumptions!$B$21)) -> 13.896372 | M13: =Assumptions!$B$17*(0.6*MIN(1,Data_Clean!R13/Assumptions!$B$22)+0.4*IF(Data_Clean!S13="",0,Data_Clean!S13)) -> 6.15 | N13: =Assumptions!$B$18*MIN(1,(Data_Clean!F13-1)/Assumptions!$B$23) -> 15 | O13: =Assumptions!$B$19*(0.4*IF(Data_Clean!E13="",0,MIN(1,Data_Clean!E13/12/Assumptions!$B$24))+0.35*IF(Data_Clean!D13="Y",1,0)+0.25*(1-MIN(Data_Clean!T13,3)/3))/IF(Data_Clean!E13="",0.6,1) -> 5.35 | P13: =SUM(K13:O13)/(Assumptions!$D$5-IF(K13="",Assumptions!$B$15,0))*100 -> 60.188991 | Q13: =IF(J13>=Assumptions!$B$26,"High",IF(J13>=Assumptions!$B$27,"Mid","Low")) -> Low | R13: =IF(P13>=Assumptions!$B$28,"High",IF(P13>=Assumptions!$B$29,"Mid","Low")) -> Mid | S13: =INDEX(Assumptions!$B$33:$B$41,MATCH(Q13&"|"&R13,Assumptions!$A$33:$A$41,0)) -> Light Touch | T13: =IF(ISNUMBER(Data_Clean!V13),J13*Data_Clean!V13,0) -> 10.042935
A14: =Data_Clean!A14 -> CX100010 | B14: =Data_Clean!G14*Assumptions!$B$5 -> 245.276 | C14: =IF(Data_Clean!H14="",0,Data_Clean!H14)*Assumptions!$B$6 -> 0 | D14: =Data_Clean!I14*Assumptions!$B$7 -> 0 | E14: =Data_Clean!J14*Assumptions!$B$8 -> 0 | F14: =Data_Clean!K14*Assumptions!$B$9 -> 0 | G14: =Data_Clean!L14*Assumptions!$B$10 -> 867.6 | H14: =IF(OR(Data_Clean!M14="",Data_Clean!N14=""),0,Data_Clean!M14*Data_Clean!N14/100)*Assumptions!$B$13*Assumptions!$B$11 -> 222.312 | I14: =Data_Clean!O14*4*Assumptions!$B$12 -> 22.43424 | J14: =SUM(B14:I14) -> 1357.6222 | K14: =IF(Data_Clean!P14="","",Assumptions!$B$15*0.5^(Data_Clean!P14/Assumptions!$B$20)) -> 17.633219 | L14: =Assumptions!$B$16*MIN(1,LN(1+Data_Clean!Q14)/LN(1+Assumptions!$B$21)) -> 13.744707 | M14: =Assumptions!$B$17*(0.6*MIN(1,Data_Clean!R14/Assumptions!$B$22)+0.4*IF(Data_Clean!S14="",0,Data_Clean!S14)) -> 7.464 | N14: =Assumptions!$B$18*MIN(1,(Data_Clean!F14-1)/Assumptions!$B$23) -> 15 | O14: =Assumptions!$B$19*(0.4*IF(Data_Clean!E14="",0,MIN(1,Data_Clean!E14/12/Assumptions!$B$24))+0.35*IF(Data_Clean!D14="Y",1,0)+0.25*(1-MIN(Data_Clean!T14,3)/3))/IF(Data_Clean!E14="",0.6,1) -> 13.7 | P14: =SUM(K14:O14)/(Assumptions!$D$5-IF(K14="",Assumptions!$B$15,0))*100 -> 67.541926 | Q14: =IF(J14>=Assumptions!$B$26,"High",IF(J14>=Assumptions!$B$27,"Mid","Low")) -> Mid | R14: =IF(P14>=Assumptions!$B$28,"High",IF(P14>=Assumptions!$B$29,"Mid","Low")) -> Mid | S14: =INDEX(Assumptions!$B$33:$B$41,MATCH(Q14&"|"&R14,Assumptions!$A$33:$A$41,0)) -> Established Core | T14: =IF(ISNUMBER(Data_Clean!V14),J14*Data_Clean!V14,0) -> 26.202109
A15: =Data_Clean!A15 -> CX100011 | B15: =Data_Clean!G15*Assumptions!$B$5 -> 155.31 | C15: =IF(Data_Clean!H15="",0,Data_Clean!H15)*Assumptions!$B$6 -> 716.64732 | D15: =Data_Clean!I15*Assumptions!$B$7 -> 0 | E15: =Data_Clean!J15*Assumptions!$B$8 -> 0 | F15: =Data_Clean!K15*Assumptions!$B$9 -> 2619.1 | G15: =Data_Clean!L15*Assumptions!$B$10 -> 0 | H15: =IF(OR(Data_Clean!M15="",Data_Clean!N15=""),0,Data_Clean!M15*Data_Clean!N15/100)*Assumptions!$B$13*Assumptions!$B$11 -> 657.12 | I15: =Data_Clean!O15*4*Assumptions!$B$12 -> 25.31904 | J15: =SUM(B15:I15) -> 4173.4964 | K15: =IF(Data_Clean!P15="","",Assumptions!$B$15*0.5^(Data_Clean!P15/Assumptions!$B$20)) -> 3.8376521 | L15: =Assumptions!$B$16*MIN(1,LN(1+Data_Clean!Q15)/LN(1+Assumptions!$B$21)) -> 13.076027 | M15: =Assumptions!$B$17*(0.6*MIN(1,Data_Clean!R15/Assumptions!$B$22)+0.4*IF(Data_Clean!S15="",0,Data_Clean!S15)) -> 8.112 | N15: =Assumptions!$B$18*MIN(1,(Data_Clean!F15-1)/Assumptions!$B$23) -> 15 | O15: =Assumptions!$B$19*(0.4*IF(Data_Clean!E15="",0,MIN(1,Data_Clean!E15/12/Assumptions!$B$24))+0.35*IF(Data_Clean!D15="Y",1,0)+0.25*(1-MIN(Data_Clean!T15,3)/3))/IF(Data_Clean!E15="",0.6,1) -> 12.25 | P15: =SUM(K15:O15)/(Assumptions!$D$5-IF(K15="",Assumptions!$B$15,0))*100 -> 52.275679 | Q15: =IF(J15>=Assumptions!$B$26,"High",IF(J15>=Assumptions!$B$27,"Mid","Low")) -> High | R15: =IF(P15>=Assumptions!$B$28,"High",IF(P15>=Assumptions!$B$29,"Mid","Low")) -> Mid | S15: =INDEX(Assumptions!$B$33:$B$41,MATCH(Q15&"|"&R15,Assumptions!$A$33:$A$41,0)) -> Established Core | T15: =IF(ISNUMBER(Data_Clean!V15),J15*Data_Clean!V15,0) -> 122.28344
A16: =Data_Clean!A16 -> CX100012 | B16: =Data_Clean!G16*Assumptions!$B$5 -> 25.41475 | C16: =IF(Data_Clean!H16="",0,Data_Clean!H16)*Assumptions!$B$6 -> 0 | D16: =Data_Clean!I16*Assumptions!$B$7 -> 0 | E16: =Data_Clean!J16*Assumptions!$B$8 -> 0 | F16: =Data_Clean!K16*Assumptions!$B$9 -> 0 | G16: =Data_Clean!L16*Assumptions!$B$10 -> 0 | H16: =IF(OR(Data_Clean!M16="",Data_Clean!N16=""),0,Data_Clean!M16*Data_Clean!N16/100)*Assumptions!$B$13*Assumptions!$B$11 -> 45.36 | I16: =Data_Clean!O16*4*Assumptions!$B$12 -> 1.42512 | J16: =SUM(B16:I16) -> 72.19987 | K16: =IF(Data_Clean!P16="","",Assumptions!$B$15*0.5^(Data_Clean!P16/Assumptions!$B$20)) -> 30 | L16: =Assumptions!$B$16*MIN(1,LN(1+Data_Clean!Q16)/LN(1+Assumptions!$B$21)) -> 11.815417 | M16: =Assumptions!$B$17*(0.6*MIN(1,Data_Clean!R16/Assumptions!$B$22)+0.4*IF(Data_Clean!S16="",0,Data_Clean!S16)) -> 8.268 | N16: =Assumptions!$B$18*MIN(1,(Data_Clean!F16-1)/Assumptions!$B$23) -> 5 | O16: =Assumptions!$B$19*(0.4*IF(Data_Clean!E16="",0,MIN(1,Data_Clean!E16/12/Assumptions!$B$24))+0.35*IF(Data_Clean!D16="Y",1,0)+0.25*(1-MIN(Data_Clean!T16,3)/3))/IF(Data_Clean!E16="",0.6,1) -> 3.9 | P16: =SUM(K16:O16)/(Assumptions!$D$5-IF(K16="",Assumptions!$B$15,0))*100 -> 58.983417 | Q16: =IF(J16>=Assumptions!$B$26,"High",IF(J16>=Assumptions!$B$27,"Mid","Low")) -> Low | R16: =IF(P16>=Assumptions!$B$28,"High",IF(P16>=Assumptions!$B$29,"Mid","Low")) -> Mid | S16: =INDEX(Assumptions!$B$33:$B$41,MATCH(Q16&"|"&R16,Assumptions!$A$33:$A$41,0)) -> Light Touch | T16: =IF(ISNUMBER(Data_Clean!V16),J16*Data_Clean!V16,0) -> 5.9348293
... A4004: =Data_Clean!A4004 -> CX104000 | B4004: =Data_Clean!G4004*Assumptions!$B$5 -> 69.8085 | C4004: =IF(Data_Clean!H4004="",0,Data_Clean!H4004)*Assumptions!$B$6 -> 115.1124 | D4004: =Data_Clean!I4004*Assumptions!$B$7 -> 0 | E4004: =Data_Clean!J4004*Assumptions!$B$8 -> 0 | F4004: =Data_Clean!K4004*Assumptions!$B$9 -> 0 | G4004: =Data_Clean!L4004*Assumptions!$B$10 -> 0 | H4004: =IF(OR(Data_Clean!M4004="",Data_Clean!N4004=""),0,Data_Clean!M4004*Data_Clean!N4004/100)*Assumptions!$B$13*Assumptions!$B$11 -> 0 | I4004: =Data_Clean!O4004*4*Assumptions!$B$12 -> 0 | J4004: =SUM(B4004:I4004) -> 184.9209 | K4004: =IF(Data_Clean!P4004="","",Assumptions!$B$15*0.5^(Data_Clean!P4004/Assumptions!$B$20)) -> 19.340555 | L4004: =Assumptions!$B$16*MIN(1,LN(1+Data_Clean!Q4004)/LN(1+Assumptions!$B$21)) -> 9.1631382 | M4004: =Assumptions!$B$17*(0.6*MIN(1,Data_Clean!R4004/Assumptions!$B$22)+0.4*IF(Data_Clean!S4004="",0,Data_Clean!S4004)) -> 5.688 | N4004: =Assumptions!$B$18*MIN(1,(Data_Clean!F4004-1)/Assumptions!$B$23) -> 5 | O4004: =Assumptions!$B$19*(0.4*IF(Data_Clean!E4004="",0,MIN(1,Data_Clean!E4004/12/Assumptions!$B$24))+0.35*IF(Data_Clean!D4004="Y",1,0)+0.25*(1-MIN(Data_Clean!T4004,3)/3))/IF(Data_Clean!E4004="",0.6,1) -> 4 | P4004: =SUM(K4004:O4004)/(Assumptions!$D$5-IF(K4004="",Assumptions!$B$15,0))*100 -> 43.191693 | Q4004: =IF(J4004>=Assumptions!$B$26,"High",IF(J4004>=Assumptions!$B$27,"Mid","Low")) -> Low | R4004: =IF(P4004>=Assumptions!$B$28,"High",IF(P4004>=Assumptions!$B$29,"Mid","Low")) -> Low | S4004: =INDEX(Assumptions!$B$33:$B$41,MATCH(Q4004&"|"&R4004,Assumptions!$A$33:$A$41,0)) -> Dormant & Low Value | T4004: =IF(ISNUMBER(Data_Clean!V4004),J4004*Data_Clean!V4004,0) -> 26.942975

Sheet Segment_Summary
A1: Segment summary – live formulas (synthetic observation)
A2: Recalculates when Assumptions change
A4: Segment | B4: Customers | C4: % of customers | D4: Est. revenue (USD) | E4: % of revenue | F4: Avg revenue / customer | G4: Avg REI | H4: Avg products | I4: % main bank | J4: Attrition next 6m (synthetic) | K4: Expected revenue at risk (model)
A5: Premier Advocates | B5: =COUNTIF(Scoring!$S$5:$S$4004,$A5) -> 554 | C5: =B5/SUM($B$5:$B$10) -> 0.1385 | D5: =SUMIF(Scoring!$S$5:$S$4004,$A5,Scoring!$J$5:$J$4004) -> 2723760.7 | E5: =D5/SUM($D$5:$D$10) -> 0.41534317 | F5: =D5/B5 -> 4916.5356 | G5: =AVERAGEIF(Scoring!$S$5:$S$4004,$A5,Scoring!$P$5:$P$4004) -> 78.584929 | H5: =AVERAGEIF(Scoring!$S$5:$S$4004,$A5,Data_Clean!$F$5:$F$4004) -> 4.5108303 | I5: =COUNTIFS(Scoring!$S$5:$S$4004,$A5,Data_Clean!$D$5:$D$4004,"Y")/B5 -> 0.76714801 | J5: =AVERAGEIF(Scoring!$S$5:$S$4004,$A5,Data_Clean!$U$5:$U$4004) -> 0.02166065 | K5: =SUMIF(Scoring!$S$5:$S$4004,$A5,Scoring!$T$5:$T$4004) -> 90480.67
A6: Established Core | B6: =COUNTIF(Scoring!$S$5:$S$4004,$A6) -> 1091 | C6: =B6/SUM($B$5:$B$10) -> 0.27275 | D6: =SUMIF(Scoring!$S$5:$S$4004,$A6,Scoring!$J$5:$J$4004) -> 2212286.8 | E6: =D6/SUM($D$5:$D$10) -> 0.33734909 | F6: =D6/B6 -> 2027.7606 | G6: =AVERAGEIF(Scoring!$S$5:$S$4004,$A6,Scoring!$P$5:$P$4004) -> 61.989372 | H6: =AVERAGEIF(Scoring!$S$5:$S$4004,$A6,Data_Clean!$F$5:$F$4004) -> 3.2053162 | I6: =COUNTIFS(Scoring!$S$5:$S$4004,$A6,Data_Clean!$D$5:$D$4004,"Y")/B6 -> 0.37213566 | J6: =AVERAGEIF(Scoring!$S$5:$S$4004,$A6,Data_Clean!$U$5:$U$4004) -> 0.077910174 | K6: =SUMIF(Scoring!$S$5:$S$4004,$A6,Scoring!$T$5:$T$4004) -> 174876.66
A7: Affluent Drifters | B7: =COUNTIF(Scoring!$S$5:$S$4004,$A7) -> 183 | C7: =B7/SUM($B$5:$B$10) -> 0.04575 | D7: =SUMIF(Scoring!$S$5:$S$4004,$A7,Scoring!$J$5:$J$4004) -> 795064.45 | E7: =D7/SUM($D$5:$D$10) -> 0.12123847 | F7: =D7/B7 -> 4344.6145 | G7: =AVERAGEIF(Scoring!$S$5:$S$4004,$A7,Scoring!$P$5:$P$4004) -> 30.7053 | H7: =AVERAGEIF(Scoring!$S$5:$S$4004,$A7,Data_Clean!$F$5:$F$4004) -> 3.6557377 | I7: =COUNTIFS(Scoring!$S$5:$S$4004,$A7,Data_Clean!$D$5:$D$4004,"Y")/B7 -> 0.18032787 | J7: =AVERAGEIF(Scoring!$S$5:$S$4004,$A7,Data_Clean!$U$5:$U$4004) -> 0.28415301 | K7: =SUMIF(Scoring!$S$5:$S$4004,$A7,Scoring!$T$5:$T$4004) -> 181161.67
A8: Engaged Builders | B8: =COUNTIF(Scoring!$S$5:$S$4004,$A8) -> 551 | C8: =B8/SUM($B$5:$B$10) -> 0.13775 | D8: =SUMIF(Scoring!$S$5:$S$4004,$A8,Scoring!$J$5:$J$4004) -> 390128.58 | E8: =D8/SUM($D$5:$D$10) -> 0.059490262 | F8: =D8/B8 -> 708.03736 | G8: =AVERAGEIF(Scoring!$S$5:$S$4004,$A8,Scoring!$P$5:$P$4004) -> 75.941403 | H8: =AVERAGEIF(Scoring!$S$5:$S$4004,$A8,Data_Clean!$F$5:$F$4004) -> 3.2976407 | I8: =COUNTIFS(Scoring!$S$5:$S$4004,$A8,Data_Clean!$D$5:$D$4004,"Y")/B8 -> 0.8384755 | J8: =AVERAGEIF(Scoring!$S$5:$S$4004,$A8,Data_Clean!$U$5:$U$4004) -> 0.02722323 | K8: =SUMIF(Scoring!$S$5:$S$4004,$A8,Scoring!$T$5:$T$4004) -> 12676.772
A9: Light Touch | B9: =COUNTIF(Scoring!$S$5:$S$4004,$A9) -> 1103 | C9: =B9/SUM($B$5:$B$10) -> 0.27575 | D9: =SUMIF(Scoring!$S$5:$S$4004,$A9,Scoring!$J$5:$J$4004) -> 364852.04 | E9: =D9/SUM($D$5:$D$10) -> 0.055635872 | F9: =D9/B9 -> 330.78155 | G9: =AVERAGEIF(Scoring!$S$5:$S$4004,$A9,Scoring!$P$5:$P$4004) -> 52.622918 | H9: =AVERAGEIF(Scoring!$S$5:$S$4004,$A9,Data_Clean!$F$5:$F$4004) -> 2.256573 | I9: =COUNTIFS(Scoring!$S$5:$S$4004,$A9,Data_Clean!$D$5:$D$4004,"Y")/B9 -> 0.3961922 | J9: =AVERAGEIF(Scoring!$S$5:$S$4004,$A9,Data_Clean!$U$5:$U$4004) -> 0.10607434 | K9: =SUMIF(Scoring!$S$5:$S$4004,$A9,Scoring!$T$5:$T$4004) -> 58447.605
A10: Dormant & Low Value | B10: =COUNTIF(Scoring!$S$5:$S$4004,$A10) -> 518 | C10: =B10/SUM($B$5:$B$10) -> 0.1295 | D10: =SUMIF(Scoring!$S$5:$S$4004,$A10,Scoring!$J$5:$J$4004) -> 71763.552 | E10: =D10/SUM($D$5:$D$10) -> 0.010943142 | F10: =D10/B10 -> 138.53968 | G10: =AVERAGEIF(Scoring!$S$5:$S$4004,$A10,Scoring!$P$5:$P$4004) -> 31.007606 | H10: =AVERAGEIF(Scoring!$S$5:$S$4004,$A10,Data_Clean!$F$5:$F$4004) -> 1.7316602 | I10: =COUNTIFS(Scoring!$S$5:$S$4004,$A10,Data_Clean!$D$5:$D$4004,"Y")/B10 -> 0.22393822 | J10: =AVERAGEIF(Scoring!$S$5:$S$4004,$A10,Data_Clean!$U$5:$U$4004) -> 0.22007722 | K10: =SUMIF(Scoring!$S$5:$S$4004,$A10,Scoring!$T$5:$T$4004) -> 15425.989
A11: Total | B11: =SUM(B5:B10) -> 4000 | C11: =SUM(C5:C10) -> 1 | D11: =SUM(D5:D10) -> 6557856.2 | E11: =SUM(E5:E10) -> 1 | K11: =SUM(K5:K10) -> 533069.36

Sheet Scenarios
A1: Hypothetical interventions – illustrative sizing (NOT results)
A2: Blue = assumption. Outcomes depend entirely on these assumptions.
A4: Scenario | B4: Assumption | C4: Value | D4: Output | E4: Result
A5: Affluent Drifters – RM re-engagement | B5: Relative cut in attrition probability | C5: 0.25 | D5: Expected annual revenue protected (USD) | E5: =Segment_Summary!K7*C5 -> 45290.418
A6: Engaged Builders – cross-sell one product | B6: Take-up rate | C6: 0.1 | D6: Incremental annual revenue (USD) | E6: =Segment_Summary!B8*C6*C7 -> 9918
B7: Annual revenue per added product (USD) | C7: 180
A9: Python reference values: Affluent Drifters: 45,290.0; Engaged Builders: 9,918.0; Light Touch: 4.8

Sheet Pilot
A1: Holdout pilot sizing (indicative)
A2: Minimum detectable change = Z × √(2·p·(1−p)/n) · Z = 2.80 for 95% confidence and 80% power
A4: Cell | B4: Eligible | C4: Treatment | D4: Holdout (n) | E4: Baseline rate (p) | F4: Min. detectable change (pts) | H4: Z | I4: 2.8
A5: Affluent Drifters RM outreach | B5: 182 | C5: 91 | D5: 91 | E5: 0.284 | F5: =$I$4*SQRT(2*E5*(1-E5)/D5)*100 -> 18.718369
A6: Light Touch digital activation | B6: 1095 | C6: 548 | D6: 547 | E6: 0.106 | F6: =$I$4*SQRT(2*E6*(1-E6)/D6)*100 -> 5.2119598
A7: Engaged Builders cross-sell | B7: 546 | C7: 273 | D7: 273 | E7: 0.05 | F7: =$I$4*SQRT(2*E7*(1-E7)/D7)*100 -> 5.2232223

Sheet Sensitivity
A1: Segmentation sensitivity (model assumption tests)
A2: Computed by src/segment.py
A4: test | B4: scenario | C4: same_segment_pct | D4: adjusted_rand_index
A5: REI weights | B5: Recency-led (40/15/15/15/15) | C5: 89.7 | D5: 0.757
A6: REI weights | B6: Adoption-led (25/15/15/30/15) | C6: 86.8 | D6: 0.707
A7: REI weights | B7: Equal weights (20 each) | C7: 88.6 | D7: 0.737
A8: REI weights | B8: No loyalty (35/25/15/25/0) | C8: 88 | D8: 0.723
A9: REI weights | B9: Digital-led (25/15/30/15/15) | C9: 84.4 | D9: 0.654
A10: Thresholds | B10: Value bands -20% | C10: 92.9 | D10: 0.836
A11: Thresholds | B11: Value bands +20% | C11: 93.9 | D11: 0.853
A12: Thresholds | B12: Engagement bands -5 pts | C12: 80.1 | D12: 0.569
A13: Thresholds | B13: Engagement bands +5 pts | C13: 79.1 | D13: 0.567
A15: k-means check: silhouette by k {'3': 0.205, '4': 0.206, '5': 0.203, '6': 0.216, '7': 0.212, '8': 0.224} · ARI rule-based vs k-means(6) = 0.184

Sheet Signals_Model
A1: Warning signals and attrition model (synthetic outcome)
A2: Logistic regression · test AUC 0.806 · top-decile lift 3.84
A4: signal | B4: customers_flagged | C4: share_of_book_pct | D4: attrition_if_present_pct | E4: attrition_if_absent_pct | F4: lift_vs_book
A5: App registered but unused 30+ days | B5: 296 | C5: 7.4 | D5: 30.1 | E5: 8.3 | F5: 3.04
A6: No transaction for 45+ days | B6: 671 | C6: 16.8 | D6: 24.9 | E6: 6.8 | F6: 2.52
A7: 2+ complaints in 12 months | B7: 131 | C7: 3.3 | D7: 21.4 | E7: 9.5 | F7: 2.16
A8: Deposits down 15%+ over 6 months | B8: 406 | C8: 10.2 | D8: 20.7 | E8: 8.7 | F8: 2.1
A9: Current account only | B9: 414 | C9: 10.4 | D9: 15.2 | E9: 9.3 | F9: 1.54
A10: Not main bank | B10: 2121 | C10: 53 | D10: 14.9 | E10: 4.2 | F10: 1.51
A11: Card utilisation 85%+ | B11: 5 | C11: 0.1 | D11: 0 | E11: 9.9 | F11: 0
A13: decile | B13: customers | C13: predicted_pct | D13: actual_pct | E13: lift
A14: 1 | B14: 119 | C14: 36.6 | D14: 37.8 | E14: 3.84
A15: 2 | B15: 120 | C15: 17.7 | D15: 19.2 | E15: 1.95
A16: 3 | B16: 120 | C16: 11.4 | D16: 16.7 | E16: 1.7
A17: 4 | B17: 120 | C17: 8.8 | D17: 5.8 | E17: 0.59
A18: 5 | B18: 120 | C18: 6.8 | D18: 6.7 | E18: 0.68
A19: 6 | B19: 119 | C19: 5.4 | D19: 4.2 | E19: 0.43
A20: 7 | B20: 120 | C20: 4.2 | D20: 2.5 | E20: 0.25
A21: 8 | B21: 120 | C21: 3.1 | D21: 1.7 | E21: 0.17
A22: 9 | B22: 120 | C22: 2.3 | D22: 3.3 | E22: 0.34
A23: 10 | B23: 120 | C23: 1.4 | D23: 0.8 | E23: 0.08
A25: feature | B25: std_coefficient
A26: rei_frequency | B26: -0.476
A27: rei_adoption | B27: -0.319
A28: main_bank | B28: -0.262
A29: deposit_change_6m_pct | B29: -0.257
A30: rei_loyalty | B30: -0.257
A31: rei_recency | B31: -0.084
A32: rei_digital | B32: -0.056
A33: log_revenue | B33: 0.155
A34: complaints_12m | B34: 0.297

Sheet DQ_Log
A1: Data-quality log
A2: 4,085 raw rows → 4,000 customers
A4: step | B4: check | C4: rule | D4: rows_affected | E4: action | F4: rationale | G4: injected_issue_key
A5: 1 | B5: Exact duplicate rows | C5: All columns identical | D5: 40 | E5: Removed (first kept) | F5: Double-loaded rows would double-count customers and balances. | G5: exact_duplicate_row
A6: 2 | B6: Re-ingested older snapshots | C6: Same customer_id appears more than once with different values | D6: 45 | E6: Kept the most recent record_updated_at; older rows removed | F6: A customer has one current state; the newest snapshot is the authoritative one. | G6: stale_snapshot_reingested
A7: 3 | B7: Region coding variants | C7: e.g. 'metro', 'METRO', 'Metropolitan', 'Rural Area' | D7: 70 | E7: Mapped to Metro / Urban / Regional / Rural | F7: Same meaning, different spelling. | G7: region_variant_coding
A8: 4 | B8: Employment text case / whitespace | C8: Upper-case values with trailing spaces | D8: 55 | E8: Trimmed and re-cased | F8: Prevents one category splitting into two. | G8: employment_case_whitespace
A9: 5 | B9: Mixed date formats (last_login_date) | C9: DD/MM/YYYY mixed with ISO YYYY-MM-DD | D9: 140 | E9: Parsed each format explicitly | F9: Guessing the format could swap day and month. | G9: login_date_ddmmyyyy
A10: 6 | B10: Transaction dated after the snapshot | C10: last_txn_date > 2026-09-30 | D10: 7 | E10: Set to missing (recency unknown); flagged | F10: A future date is impossible; the true date is unknown. | G10: last_txn_after_snapshot
A11: 7 | B11: Impossible age | C11: age < 18 or > 105 (values 0, 150, 999) | D11: 9 | E11: Set to missing | F11: Looks like sentinel / keying values; true age unknown. Age is not used in the segmentation. | G11: age_sentinel_or_impossible
A12: 8 | B12: Sentinel tenure | C12: tenure_months = -1 | D12: 24 | E12: Set to missing; loyalty score uses observed components only | F12: -1 is a system placeholder for 'unknown'. | G12: tenure_sentinel_minus_one
A13: 9 | B13: Income recorded in thousands | C13: annual_income < 1,000 for a non-student (e.g. 54.3) | D13: 36 | E13: Multiplied by 1,000 | F13: Values are plausible incomes once read as thousands; no annual income below USD 1,000 is credible for an earning adult. Income is descriptive only (not in the score). | G13: income_recorded_in_thousands
A14: 10 | B14: Income missing | C14: annual_income blank | D14: 150 | E14: Left missing (not imputed) | F14: Income is not used in the segmentation, so no estimate is needed. | G14: income_missing
A15: 11 | B15: Impossible card utilisation | C15: card_utilisation_pct > 150% | D15: 14 | E15: Set to missing | F15: Small over-limit use is possible; 160–900% is not. | G15: card_utilisation_impossible
A16: 12 | B16: Card holder without a limit | C16: has_credit_card = 1 and credit_card_limit blank | D16: 11 | E16: Left missing; revolving-balance revenue scored as 0 for these rows and flagged | F16: Limit unknown – no value is invented. | G16: card_limit_missing
... A18: 14 | B18: Negative savings balance | C18: savings_balance < 0 | D18: 18 | E18: 5 rows with no savings product set to 0; 13 rows with a savings product set to missing | F18: Savings accounts cannot be negative. With no product the balance must be 0; otherwise the true value is unknown. | G18: savings_balance_negative
A19: 15 | B19: Row count reconciliation | C19: 4,085 raw rows → 4,000 customers | D19: 85 | E19: Removed rows = exact duplicates + stale snapshots | F19: Every customer_id is now unique.

Sheet Data_Dictionary
A1: Data dictionary
A2: Synthetic fields
A4: field | B4: type | C4: description
A5: customer_id | B5: text | C5: Fictional pseudonymous customer identifier (CX100001–CX104000). No names or contact details are generated.
A6: record_updated_at | B6: date | C6: Date the source record was last refreshed (used to resolve re-ingested snapshots)
A7: age | B7: integer | C7: Customer age in years (synthetic)
A8: gender | B8: category | C8: Female / Male / Non-binary or undisclosed (synthetic; descriptive only, never used in scoring)
A9: region | B9: category | C9: Metro / Urban / Regional / Rural
A10: employment_type | B10: category | C10: Salaried, Self-employed, Business owner, Retired, Student, Not employed
A11: annual_income | B11: number (USD) | C11: Stated annual income (synthetic; descriptive only)
A12: tenure_months | B12: integer | C12: Months since the relationship began
A13: onboarding_channel | B13: category | C13: Digital / Branch / Partner
A14: main_bank_flag | B14: Y/N | C14: Salary or main income credited to this bank
A15: has_savings … has_insurance | B15: 0/1 | C15: Product holding flags (savings; term deposit; credit card; personal loan; mortgage; investments; insurance)
... A36: dq_flags | B36: text | C36: Cleaning flags applied to the record
